preprocessing
stylelens_color
test
