Metadata-Version: 1.0
Name: stylelens-color
Version: 1.0.2
Summary: stylelens-color
Home-page: UNKNOWN
Author: UNKNOWN
Author-email: lion@bluehack.net
License: UNKNOWN
Keywords: Swagger,stylelens-color
Platform: UNKNOWN
